README.md
setup.py
DataGun.egg-info/PKG-INFO
DataGun.egg-info/SOURCES.txt
DataGun.egg-info/dependency_links.txt
DataGun.egg-info/not-zip-safe
DataGun.egg-info/requires.txt
DataGun.egg-info/top_level.txt
datagun/__init__.py
datagun/datagun.py