Metadata-Version: 2.1
Name: DataGun
Version: 0.1.0
Summary: Data converter
Home-page: https://github.com/pavelmaksimov/datagun
Author: Pavel Maksimov
Author-email: vur21@ya.ru
License: MIT
Keywords: datagun,data,transform,transformer,deserialize,serialize
Platform: UNKNOWN
Provides-Extra: pandas
